{
  "shadows_4_": {
    "width": 33.41464,
    "height": 13.47277,
    "x": 93.30359,
    "y": -22.038125
  },
  "shadows_6_": {
    "width": 27.30801,
    "height": 13.47277,
    "x": 121.41790499999999,
    "y": -39.116345
  },
  "shadows_5_": {
    "width": 17.67389,
    "height": 49.83152,
    "x": 147.60242499999998,
    "y": -26.473779999999998
  },
  "shadows_1_": {
    "width": 33.41465,
    "height": 39.70409,
    "x": 18.120735,
    "y": -99.291135
  },
  "shadows_2_": {
    "width": 24.293409999999998,
    "height": 17.13367,
    "x": 60.974435,
    "y": -91.65573499999999
  },
  "groundcage1_27_": {
    "width": 8.35366,
    "height": 3.05416,
    "x": 30.65122,
    "y": -117.61609
  },
  "groundcage3": {
    "width": 8.35366,
    "height": 3.05416,
    "x": 30.65122,
    "y": -114.56193
  },
  "groundcage3_1_": {
    "width": 8.35366,
    "height": 3.05416,
    "x": 30.65122,
    "y": -111.50777
  },
  "groundcage3_2_": {
    "width": 8.35366,
    "height": 3.05416,
    "x": 30.65122,
    "y": -108.45361
  },
  "groundcage3_3_": {
    "width": 8.35366,
    "height": 3.05416,
    "x": 30.65122,
    "y": -105.39944999999999
  },
  "groundcage3_4_": {
    "width": 8.35366,
    "height": 3.05416,
    "x": 30.65122,
    "y": -102.34528999999999
  },
  "groundcage3_9_": {
    "width": 8.35366,
    "height": 3.05416,
    "x": 5.59024,
    "y": -114.56193
  },
  "groundcage3_8_": {
    "width": 8.35366,
    "height": 3.05416,
    "x": 5.59024,
    "y": -111.50777
  },
  "groundcage3_7_": {
    "width": 8.35366,
    "height": 3.05416,
    "x": 5.59024,
    "y": -108.45361
  },
  "groundcage3_6_": {
    "width": 8.35366,
    "height": 3.05416,
    "x": 5.59024,
    "y": -105.39944999999999
  },
  "groundcage3_5_": {
    "width": 8.35366,
    "height": 3.05416,
    "x": 5.59024,
    "y": -102.34528999999999
  },
  "groundcage3_14_": {
    "width": 8.35366,
    "height": 3.05416,
    "x": 5.59024,
    "y": -99.29113000000001
  },
  "groundcage3_13_": {
    "width": 8.35366,
    "height": 3.05416,
    "x": 5.59024,
    "y": -96.23697
  },
  "groundcage3_12_": {
    "width": 8.35366,
    "height": 3.05416,
    "x": 5.59024,
    "y": -93.18281
  },
  "groundcage3_11_": {
    "width": 8.35366,
    "height": 3.05416,
    "x": 5.59024,
    "y": -90.12865
  },
  "groundcage3_10_": {
    "width": 8.35366,
    "height": 3.05416,
    "x": 5.59024,
    "y": -87.07449
  },
  "groundcage3_15_": {
    "width": 8.35366,
    "height": 3.05416,
    "x": 5.59024,
    "y": -84.02033
  },
  "groundcage1_3_": {
    "width": 8.35366,
    "height": 3.05416,
    "x": 39.00489,
    "y": -117.61609
  },
  "groundcage1_2_": {
    "width": 8.35366,
    "height": 3.05416,
    "x": 47.35856,
    "y": -117.61609
  },
  "groundcage4_1_": {
    "width": 8.35366,
    "height": 3.05416,
    "x": 55.71222,
    "y": -117.61609
  },
  "groundcage1_4_": {
    "width": 8.35366,
    "height": 3.05416,
    "x": 64.0659,
    "y": -117.61609
  },
  "groundcage1_13_": {
    "width": 8.35367,
    "height": 3.05416,
    "x": 47.35856499999999,
    "y": -108.45361
  },
  "groundcage1_15_": {
    "width": 8.35364,
    "height": 3.05416,
    "x": 72.41954000000001,
    "y": -117.61609
  },
  "groundcage1_25_": {
    "width": 8.35364,
    "height": 3.05416,
    "x": 72.41954000000001,
    "y": -80.96616999999999
  },
  "groundcage3_113_": {
    "width": 8.35366,
    "height": 3.05416,
    "x": 47.35856,
    "y": -80.96616999999999
  },
  "platformcage3_2_": {
    "width": 3.6341300000000003,
    "height": 2.06352,
    "x": 66.425645,
    "y": -110.93699
  },
  "platformcage3_1_": {
    "width": 3.6341300000000003,
    "height": 2.06352,
    "x": 62.791515,
    "y": -110.93699
  },
  "platformcage3_6_": {
    "width": 3.63412,
    "height": 2.06352,
    "x": 66.42564,
    "y": -98.51292000000001
  },
  "platformcage3_5_": {
    "width": 3.6341300000000003,
    "height": 2.06352,
    "x": 62.791505,
    "y": -98.51292000000001
  },
  "platformcage3_7_": {
    "width": 3.6341300000000003,
    "height": 2.06352,
    "x": 56.986595,
    "y": -104.70348000000001
  },
  "platformcage3_3_": {
    "width": 3.6341300000000003,
    "height": 2.06352,
    "x": 53.352455,
    "y": -104.70348000000001
  },
  "platformcage3_8_": {
    "width": 3.6341300000000003,
    "height": 2.06352,
    "x": 66.425625,
    "y": -86.08885000000001
  },
  "platformcage3_4_": {
    "width": 3.63414,
    "height": 2.06352,
    "x": 62.79149,
    "y": -86.08885000000001
  },
  "platformcage3_15_": {
    "width": 3.6341300000000003,
    "height": 2.06352,
    "x": 56.986595,
    "y": -77.41664000000002
  },
  "platformcage3_14_": {
    "width": 3.6341300000000003,
    "height": 2.06352,
    "x": 53.352455,
    "y": -77.41664000000002
  },
  "groundcage2": {
    "width": 8.35365,
    "height": 3.05416,
    "x": 39.004895,
    "y": -80.96616999999999
  },
  "groundcage1_48_": {
    "width": 8.35366,
    "height": 3.05416,
    "x": 22.29756,
    "y": -117.61609
  },
  "groundcage1_65_": {
    "width": 8.35366,
    "height": 3.05416,
    "x": 13.9439,
    "y": -117.61609
  },
  "groundcage4_2_": {
    "width": 8.35366,
    "height": 3.05416,
    "x": 13.9439,
    "y": -117.61609
  },
  "groundcage1_64_": {
    "width": 8.35366,
    "height": 3.05416,
    "x": 5.59024,
    "y": -117.61609
  },
  "pillevolutionb_2_": {
    "width": 0.50686,
    "height": 0.61859,
    "x": 42.17808,
    "y": -114.34306500000001
  },
  "pillevolutionb_3_": {
    "width": 0.50686,
    "height": 0.61858,
    "x": 82.04755,
    "y": -74.38641000000001
  },
  "groundcage1_61_": {
    "width": 8.35367,
    "height": 3.05416,
    "x": 80.77320499999999,
    "y": -80.96616999999999
  },
  "groundcage4_3_": {
    "width": 8.35367,
    "height": 3.05416,
    "x": 89.126875,
    "y": -80.96616999999999
  },
  "groundcage1_59_": {
    "width": 8.35366,
    "height": 3.05416,
    "x": 97.48053999999999,
    "y": -80.96616999999999
  },
  "groundcage1_58_": {
    "width": 8.35365,
    "height": 3.05416,
    "x": 105.83419499999998,
    "y": -80.96616999999999
  },
  "groundcage1_57_": {
    "width": 8.35367,
    "height": 3.05416,
    "x": 114.18786499999999,
    "y": -80.96616999999999
  },
  "groundcage1_46_": {
    "width": 8.35365,
    "height": 3.05416,
    "x": 122.541485,
    "y": -80.96616999999999
  },
  "groundcage1_24_": {
    "width": 8.35367,
    "height": 3.05416,
    "x": 130.895145,
    "y": -80.96616999999999
  },
  "groundcage1_11_": {
    "width": 8.35367,
    "height": 3.05416,
    "x": 139.248815,
    "y": -80.96616999999999
  },
  "groundcage1_69_": {
    "width": 8.35367,
    "height": 3.05416,
    "x": 147.60247500000003,
    "y": -80.96616999999999
  },
  "platformcage1_12_": {
    "width": 3.63414,
    "height": 2.06351,
    "x": 89.3158,
    "y": -76.343655
  },
  "platformcage2_26_": {
    "width": 3.63411,
    "height": 2.0635,
    "x": 96.58406499999998,
    "y": -76.34365
  },
  "platformcage2_76_": {
    "width": 3.63412,
    "height": 2.06351,
    "x": 96.58407999999999,
    "y": -74.28015500000001
  },
  "platformcage2_1_": {
    "width": 3.6341,
    "height": 2.06353,
    "x": 96.58405,
    "y": -59.835544999999996
  },
  "platformcage2_33_": {
    "width": 3.6341,
    "height": 2.06354,
    "x": 107.48645,
    "y": -68.0896
  },
  "platformcage2_32_": {
    "width": 3.63412,
    "height": 2.06351,
    "x": 107.48644,
    "y": -66.02608500000001
  },
  "platformcage2_31_": {
    "width": 3.63414,
    "height": 2.06352,
    "x": 107.48647000000001,
    "y": -63.96257
  },
  "platformcage2_6_": {
    "width": 3.63414,
    "height": 2.06352,
    "x": 107.48647000000001,
    "y": -55.70851
  },
  "platformcage1_90_": {
    "width": 3.63414,
    "height": 2.06354,
    "x": 103.85233,
    "y": -76.34366999999999
  },
  "platformcage1_4_": {
    "width": 3.63412,
    "height": 2.06354,
    "x": 103.85231999999999,
    "y": -78.40728999999999
  },
  "platformcage1_89_": {
    "width": 3.63414,
    "height": 2.06351,
    "x": 103.85233,
    "y": -74.28015500000001
  },
  "platformcage1_28_": {
    "width": 3.63414,
    "height": 2.06351,
    "x": 103.85233,
    "y": -72.216645
  },
  "platformcage2_38_": {
    "width": 3.63412,
    "height": 2.06351,
    "x": 103.85231999999999,
    "y": -66.02608500000001
  },
  "platformcage2_9_": {
    "width": 3.63412,
    "height": 2.0635,
    "x": 125.65702999999999,
    "y": -78.40729
  },
  "platformcage2_21_": {
    "width": 3.63415,
    "height": 2.06353,
    "x": 118.388795,
    "y": -72.21670499999999
  },
  "platformcage1_59_": {
    "width": 3.63415,
    "height": 2.06352,
    "x": 118.388795,
    "y": -63.962630000000004
  },
  "platformcage4_7_": {
    "width": 3.63414,
    "height": 2.06354,
    "x": 82.04756,
    "y": -78.40728999999999
  },
  "platformcage4_13_": {
    "width": 3.63414,
    "height": 2.06353,
    "x": 82.04756,
    "y": -76.34375499999999
  },
  "platformcage3_19_": {
    "width": 3.63414,
    "height": 2.06352,
    "x": 89.3158,
    "y": -70.15314000000001
  },
  "platformcage3_12_": {
    "width": 3.63414,
    "height": 2.06353,
    "x": 89.3158,
    "y": -72.23166499999999
  },
  "platformcage2_5_": {
    "width": 3.63414,
    "height": 2.06354,
    "x": 89.3158,
    "y": -68.08961
  },
  "platformcage4_20_": {
    "width": 3.63414,
    "height": 2.06353,
    "x": 89.3158,
    "y": -74.28016500000001
  },
  "platformcage4_21_": {
    "width": 3.63414,
    "height": 2.06354,
    "x": 89.3158,
    "y": -78.40728999999999
  },
  "platformcage4_22_": {
    "width": 3.6341300000000003,
    "height": 2.06352,
    "x": 96.584035,
    "y": -72.23167000000001
  },
  "platformcage4_23_": {
    "width": 3.63414,
    "height": 2.06354,
    "x": 96.58407000000001,
    "y": -78.40728999999999
  },
  "platformcage4_24_": {
    "width": 3.63412,
    "height": 2.06353,
    "x": 96.58407999999999,
    "y": -68.089605
  },
  "platformcage1_1_": {
    "width": 3.63414,
    "height": 2.06352,
    "x": 96.58407000000001,
    "y": -70.15314000000001
  },
  "platformcage3_11_": {
    "width": 3.63412,
    "height": 2.06353,
    "x": 96.58407999999999,
    "y": -63.955054999999994
  },
  "platformcage3_10_": {
    "width": 3.63412,
    "height": 2.06352,
    "x": 96.58407999999999,
    "y": -66.03359
  },
  "platformcage3_9_": {
    "width": 3.63412,
    "height": 2.06353,
    "x": 96.58407999999999,
    "y": -61.899074999999996
  },
  "platformcage3_16_": {
    "width": 3.63414,
    "height": 2.06352,
    "x": 103.85230999999999,
    "y": -55.70851
  },
  "platformcage3_17_": {
    "width": 3.63414,
    "height": 2.06352,
    "x": 103.85230999999999,
    "y": -57.77202
  },
  "platformcage3_18_": {
    "width": 3.63412,
    "height": 2.06352,
    "x": 107.48646000000001,
    "y": -57.77202
  },
  "platformcage3_20_": {
    "width": 3.63412,
    "height": 2.06352,
    "x": 107.48646000000001,
    "y": -59.835539999999995
  },
  "platformcage3_26_": {
    "width": 3.63414,
    "height": 2.06353,
    "x": 125.65704,
    "y": -68.089665
  },
  "platformcage3_25_": {
    "width": 3.63414,
    "height": 2.06353,
    "x": 125.65704,
    "y": -70.15318500000001
  },
  "platformcage3_28_": {
    "width": 3.63415,
    "height": 2.06353,
    "x": 118.388795,
    "y": -74.28025500000001
  },
  "platformcage3_29_": {
    "width": 3.63414,
    "height": 2.06353,
    "x": 125.65704,
    "y": -74.28025500000001
  },
  "platformcage3_30_": {
    "width": 3.63414,
    "height": 2.06352,
    "x": 125.65702,
    "y": -72.21671
  },
  "platformcage3_27_": {
    "width": 3.63415,
    "height": 2.06353,
    "x": 118.388795,
    "y": -76.34376499999999
  },
  "platformcage3_22_": {
    "width": 3.63412,
    "height": 2.06353,
    "x": 107.48646000000001,
    "y": -74.28016500000001
  },
  "platformcage3_23_": {
    "width": 3.63414,
    "height": 2.06354,
    "x": 107.48644,
    "y": -76.34365
  },
  "platformcage3_24_": {
    "width": 3.63412,
    "height": 2.06354,
    "x": 107.48646000000001,
    "y": -78.40728999999999
  },
  "platformcage4_25_": {
    "width": 3.6341300000000003,
    "height": 2.06352,
    "x": 96.584035,
    "y": -57.77202
  },
  "platformcage4_28_": {
    "width": 3.63414,
    "height": 2.06353,
    "x": 103.85233,
    "y": -59.835544999999996
  },
  "platformcage4_29_": {
    "width": 3.63414,
    "height": 2.06353,
    "x": 103.85230999999999,
    "y": -61.899074999999996
  },
  "platformcage4_46_": {
    "width": 3.63415,
    "height": 2.06352,
    "x": 118.388795,
    "y": -66.02614000000001
  },
  "platformcage4_45_": {
    "width": 3.6341699999999997,
    "height": 2.06353,
    "x": 118.388765,
    "y": -68.089665
  },
  "platformcage4_63_": {
    "width": 3.63415,
    "height": 2.06353,
    "x": 118.36461500000001,
    "y": -61.899055000000004
  },
  "platformcage4_47_": {
    "width": 3.63415,
    "height": 2.06352,
    "x": 118.388795,
    "y": -70.15318
  },
  "platformcage4_32_": {
    "width": 3.63414,
    "height": 2.06353,
    "x": 103.85230999999999,
    "y": -68.089605
  },
  "platformcage4_31_": {
    "width": 3.63414,
    "height": 2.06352,
    "x": 103.85233,
    "y": -63.96257
  },
  "platformcage4_33_": {
    "width": 3.63414,
    "height": 2.06352,
    "x": 103.85233,
    "y": -70.15314000000001
  },
  "platformcage4_34_": {
    "width": 3.63412,
    "height": 2.06352,
    "x": 107.48646000000001,
    "y": -70.15314000000001
  },
  "platformcage4_35_": {
    "width": 3.63414,
    "height": 2.06352,
    "x": 107.48644,
    "y": -72.23167000000001
  },
  "platformcage4_30_": {
    "width": 3.63412,
    "height": 2.06353,
    "x": 107.48644,
    "y": -61.899074999999996
  },
  "platformcage4_48_": {
    "width": 3.6341699999999997,
    "height": 2.06352,
    "x": 118.388765,
    "y": -78.40728
  },
  "platformcage4_49_": {
    "width": 3.63414,
    "height": 2.06353,
    "x": 125.65702,
    "y": -76.34376499999999
  },
  "platformcage4_26_": {
    "width": 3.6341300000000003,
    "height": 2.06352,
    "x": 96.584035,
    "y": -55.70851
  },
  "spadesdown": {
    "width": 3.63412,
    "height": 0.35983,
    "x": 78.41342999999999,
    "y": -79.25913499999999
  },
  "spadesdown_1_": {
    "width": 3.6341,
    "height": 0.35983,
    "x": 85.68167999999999,
    "y": -79.259175
  },
  "spadesdown_2_": {
    "width": 3.63411,
    "height": 0.35983,
    "x": 92.949925,
    "y": -79.25913499999999
  },
  "spadesdown_3_": {
    "width": 3.63412,
    "height": 0.35983,
    "x": 100.2182,
    "y": -79.25913499999999
  },
  "spadesdown_4_": {
    "width": 3.6341,
    "height": 0.35982,
    "x": 111.12056,
    "y": -79.25912000000001
  },
  "spadesdown_5_": {
    "width": 3.63412,
    "height": 0.35982,
    "x": 114.75469000000001,
    "y": -79.25912000000001
  },
  "spadesdown_6_": {
    "width": 3.63409,
    "height": 0.35982,
    "x": 122.02290499999998,
    "y": -79.25912000000001
  },
  "spadesdown_7_": {
    "width": 3.6341,
    "height": 0.35982,
    "x": 129.29116,
    "y": -79.25912000000001
  },
  "spadesdown_8_": {
    "width": 3.6341,
    "height": 0.35982,
    "x": 132.9253,
    "y": -79.25912000000001
  },
  "spadesdown_9_": {
    "width": 3.6341,
    "height": 0.35982,
    "x": 136.55948,
    "y": -79.25912000000001
  },
  "spadesdown_29_": {
    "width": 3.6341,
    "height": 0.35982,
    "x": 140.19359,
    "y": -79.25912000000001
  },
  "spadesdown_30_": {
    "width": 3.6341,
    "height": 0.35982,
    "x": 143.8277,
    "y": -79.25912000000001
  },
  "end_2_": {
    "width": 2.51266,
    "height": 4.03363,
    "x": 17.320019999999996,
    "y": -114.03377499999999
  },
  "shadows_3_": {
    "width": 25.061030000000002,
    "height": 25.930439999999997,
    "x": 39.004875,
    "y": -63.41966000000001
  },
  "pillevolutiond_1_": {
    "width": 0.50683,
    "height": 0.6185499999999999,
    "x": 39.004875,
    "y": -70.625405
  },
  "groundcage1_131_": {
    "width": 8.35364,
    "height": 3.05418,
    "x": 55.71216,
    "y": -66.67267
  },
  "groundcage3_114_": {
    "width": 8.35364,
    "height": 3.05418,
    "x": 55.71215,
    "y": -51.401849999999996
  },
  "platformcage2_11_": {
    "width": 3.63412,
    "height": 2.06352,
    "x": 39.193859999999994,
    "y": -72.84973000000001
  },
  "platformcage2_49_": {
    "width": 3.63416,
    "height": 2.0635499999999998,
    "x": 28.29146,
    "y": -64.595625
  },
  "pillevolutionb_4_": {
    "width": 0.50686,
    "height": 0.61857,
    "x": 36.07383,
    "y": -70.625395
  },
  "platformcage4_50_": {
    "width": 3.63415,
    "height": 2.06354,
    "x": 35.559715000000004,
    "y": -72.84969999999998
  },
  "platformcage4_27_": {
    "width": 3.63414,
    "height": 2.06352,
    "x": 31.92557,
    "y": -70.78617
  },
  "platformcage4_2_": {
    "width": 3.63414,
    "height": 2.06352,
    "x": 49.718340000000005,
    "y": -63.56738
  },
  "platformcage4_53_": {
    "width": 3.63414,
    "height": 2.06352,
    "x": 28.291430000000002,
    "y": -70.78617
  },
  "platformcage3_31_": {
    "width": 3.63412,
    "height": 2.06354,
    "x": 28.29146,
    "y": -66.65916999999999
  },
  "platformcage3_34_": {
    "width": 3.6341300000000003,
    "height": 2.06354,
    "x": 49.718335,
    "y": -61.500319999999995
  },
  "platformcage3_32_": {
    "width": 3.63412,
    "height": 2.06354,
    "x": 28.29146,
    "y": -72.84974
  },
  "platformcage3_33_": {
    "width": 3.63412,
    "height": 2.06354,
    "x": 31.92554,
    "y": -72.84974
  },
  "platformcage2_2_": {
    "width": 3.6341300000000003,
    "height": 2.06352,
    "x": 49.718335,
    "y": -65.62742
  },
  "platformcage4_1_": {
    "width": 3.63416,
    "height": 2.06354,
    "x": 46.084179999999996,
    "y": -65.62738999999999
  },
  "platformcage3_21_": {
    "width": 3.6341300000000003,
    "height": 2.06354,
    "x": 42.450015,
    "y": -65.62742999999999
  },
  "platformcage4_51_": {
    "width": 3.63414,
    "height": 2.06352,
    "x": 28.29145,
    "y": -68.72266
  },
  "platformcage1_5_": {
    "width": 3.63418,
    "height": 2.06354,
    "x": 46.084179999999996,
    "y": -63.56386
  },
  "spadesdown_24_": {
    "width": 3.63412,
    "height": 0.35982,
    "x": 35.559689999999996,
    "y": -76.20497
  },
  "spadesdown_23_": {
    "width": 3.63411,
    "height": 0.35984,
    "x": 39.193825000000004,
    "y": -76.20496
  },
  "spadesdown_28_": {
    "width": 3.63411,
    "height": 0.35982,
    "x": 28.291435,
    "y": -76.20497
  },
  "spadesdown_27_": {
    "width": 3.63411,
    "height": 0.35984,
    "x": 31.925575,
    "y": -76.20496
  },
  "spadesleft_1_": {
    "width": 0.35590000000000005,
    "height": 2.06354,
    "x": 26.65235,
    "y": -62.17577
  },
  "spadesleft_2_": {
    "width": 0.35590000000000005,
    "height": 2.06353,
    "x": 26.65235,
    "y": -60.112244999999994
  },
  "spadesleft_4_": {
    "width": 0.35590000000000005,
    "height": 2.06354,
    "x": 26.65235,
    "y": -58.087770000000006
  },
  "spadesleft_3_": {
    "width": 0.35590000000000005,
    "height": 2.06354,
    "x": 26.65235,
    "y": -56.02423
  },
  "spadesleft_5_": {
    "width": 0.35590000000000005,
    "height": 2.06354,
    "x": 26.65235,
    "y": -53.9607
  },
  "spadesleft_8_": {
    "width": 0.35590000000000005,
    "height": 2.06354,
    "x": 38.640080000000005,
    "y": -56.762010000000004
  },
  "spadesleft_7_": {
    "width": 0.35590000000000005,
    "height": 2.06354,
    "x": 38.640080000000005,
    "y": -54.69848
  },
  "spadesleft_6_": {
    "width": 0.35590000000000005,
    "height": 2.06354,
    "x": 38.640080000000005,
    "y": -52.63494
  },
  "spadesdown_10_": {
    "width": 3.63414,
    "height": 0.35983,
    "x": 40.2792,
    "y": -57.973695
  },
  "pillevolutiond_2_": {
    "width": 0.50684,
    "height": 0.6185499999999999,
    "x": 46.08419,
    "y": -61.144005
  },
  "pillevolutionb_5_": {
    "width": 0.50686,
    "height": 0.61856,
    "x": 49.718340000000005,
    "y": -59.57372000000001
  },
  "platformcage4_3_": {
    "width": 3.63414,
    "height": 2.06352,
    "x": 36.64506,
    "y": -53.01329
  },
  "platformcage4_4_": {
    "width": 3.63414,
    "height": 2.06352,
    "x": 36.64506,
    "y": -55.07681
  },
  "platformcage4_5_": {
    "width": 3.63414,
    "height": 2.06352,
    "x": 36.64506,
    "y": -57.140319999999996
  },
  "platformcage4_8_": {
    "width": 3.63414,
    "height": 2.06352,
    "x": 36.64506,
    "y": -59.18537
  },
  "platformcage4_9_": {
    "width": 3.63415,
    "height": 2.06352,
    "x": 40.279205000000005,
    "y": -59.18537
  },
  "groundcage1_126_": {
    "width": 8.35364,
    "height": 3.05416,
    "x": 122.54143,
    "y": -47.37040999999999
  },
  "groundcage4_4_": {
    "width": 8.35366,
    "height": 3.05416,
    "x": 97.48042,
    "y": -47.37040999999999
  },
  "groundcage1_124_": {
    "width": 8.35364,
    "height": 3.05416,
    "x": 89.12676000000002,
    "y": -47.37040999999999
  },
  "groundcage1_123_": {
    "width": 8.35366,
    "height": 3.05416,
    "x": 80.7731,
    "y": -47.37040999999999
  },
  "groundcage1_122_": {
    "width": 8.35365,
    "height": 3.05416,
    "x": 130.89506500000002,
    "y": -47.37040999999999
  },
  "platformcage4_62_": {
    "width": 3.63414,
    "height": 2.06352,
    "x": 97.59314,
    "y": -42.21163
  },
  "platformcage4_61_": {
    "width": 3.63412,
    "height": 2.06352,
    "x": 105.94683,
    "y": -38.08459
  },
  "platformcage4_60_": {
    "width": 3.63414,
    "height": 2.06352,
    "x": 89.23949,
    "y": -38.08459
  },
  "platformcage4_59_": {
    "width": 3.63412,
    "height": 2.06352,
    "x": 105.94683,
    "y": -21.576469999999997
  },
  "platformcage4_58_": {
    "width": 3.63414,
    "height": 2.06352,
    "x": 89.23949,
    "y": -21.576469999999997
  },
  "platformcage4_57_": {
    "width": 3.63414,
    "height": 2.06352,
    "x": 97.59314,
    "y": -33.95756
  },
  "platformcage4_56_": {
    "width": 3.63414,
    "height": 2.06351,
    "x": 89.23949,
    "y": -29.830525
  },
  "platformcage4_55_": {
    "width": 3.63412,
    "height": 2.06351,
    "x": 105.94683,
    "y": -29.830525
  },
  "platformcage4_54_": {
    "width": 3.63414,
    "height": 2.06352,
    "x": 97.59314,
    "y": -25.7035
  },
  "platformcage4_52_": {
    "width": 3.63414,
    "height": 2.06352,
    "x": 105.94682,
    "y": -13.322400000000002
  },
  "platformcage4_44_": {
    "width": 3.63412,
    "height": 2.06352,
    "x": 89.23948,
    "y": -21.576469999999997
  },
  "platformcage4_43_": {
    "width": 3.63414,
    "height": 2.06352,
    "x": 105.94682,
    "y": -21.576469999999997
  },
  "platformcage4_42_": {
    "width": 3.6341300000000003,
    "height": 2.06352,
    "x": 97.593135,
    "y": -17.44944
  },
  "platformcage4_41_": {
    "width": 3.6341300000000003,
    "height": 2.06352,
    "x": 114.30048500000001,
    "y": -42.21163
  },
  "platformcage4_40_": {
    "width": 3.63416,
    "height": 2.06352,
    "x": 122.65418,
    "y": -38.08459
  },
  "platformcage4_39_": {
    "width": 3.6341300000000003,
    "height": 2.06352,
    "x": 114.30048500000001,
    "y": -33.95756
  },
  "platformcage4_38_": {
    "width": 3.63416,
    "height": 2.06351,
    "x": 122.65418,
    "y": -29.830525
  },
  "platformcage4_37_": {
    "width": 3.6341300000000003,
    "height": 2.06352,
    "x": 114.30048500000001,
    "y": -25.7035
  },
  "platformcage4_36_": {
    "width": 3.63414,
    "height": 2.06352,
    "x": 131.00781,
    "y": -42.21163
  },
  "platformcage4_19_": {
    "width": 3.63414,
    "height": 2.06352,
    "x": 131.00781,
    "y": -33.95756
  },
  "platformcage4_18_": {
    "width": 3.63414,
    "height": 2.06352,
    "x": 131.00781,
    "y": -25.7035
  },
  "platformcage4_17_": {
    "width": 3.6341699999999997,
    "height": 2.06352,
    "x": 122.65417500000001,
    "y": -21.576469999999997
  },
  "platformcage4_15_": {
    "width": 3.6341300000000003,
    "height": 2.06352,
    "x": 114.30048500000001,
    "y": -17.44944
  },
  "platformcage4_14_": {
    "width": 3.6341300000000003,
    "height": 2.06352,
    "x": 114.30050499999999,
    "y": -17.44944
  },
  "platformcage4_12_": {
    "width": 3.63415,
    "height": 2.06352,
    "x": 122.654205,
    "y": -13.322400000000002
  },
  "platformcage4_16_": {
    "width": 3.6341300000000003,
    "height": 2.06352,
    "x": 114.30050499999999,
    "y": -9.19537
  },
  "platformcage4_11_": {
    "width": 3.6341,
    "height": 2.06352,
    "x": 131.00790999999998,
    "y": -9.19537
  },
  "groundcage2_31_": {
    "width": 8.35367,
    "height": 3.05416,
    "x": 80.773095,
    "y": -13.774650000000001
  },
  "groundcage3_89_": {
    "width": 8.35367,
    "height": 3.05416,
    "x": 72.419435,
    "y": -15.301739999999999
  },
  "groundcage3_87_": {
    "width": 8.35366,
    "height": 3.05416,
    "x": 97.48039999999999,
    "y": -4.61217
  },
  "groundcage1_91_": {
    "width": 8.35365,
    "height": 3.05416,
    "x": 139.248725,
    "y": -10.72989
  },
  "groundcage1_97_": {
    "width": 8.35365,
    "height": 3.05416,
    "x": 139.248725,
    "y": -47.37040999999999
  },
  "groundcage1_100_": {
    "width": 8.35366,
    "height": 3.05416,
    "x": 155.95611,
    "y": -50.424569999999996
  },
  "groundcage2_12_": {
    "width": 8.35365,
    "height": 3.05416,
    "x": 139.248725,
    "y": -50.424569999999996
  },
  "groundcage4_5_": {
    "width": 8.35365,
    "height": 3.05416,
    "x": 147.602425,
    "y": -50.424569999999996
  },
  "spadesdown_26_": {
    "width": 3.61508,
    "height": 0.35795,
    "x": 145.23315,
    "y": -48.718515
  },
  "spadesdown_25_": {
    "width": 3.61508,
    "height": 0.35795,
    "x": 148.84821999999997,
    "y": -48.718515
  },
  "spadesdown_22_": {
    "width": 3.6151,
    "height": 0.35795,
    "x": 152.46330999999998,
    "y": -48.718515
  },
  "pillevolutiond_4_": {
    "width": 0.50684,
    "height": 0.6185499999999999,
    "x": 141.07229,
    "y": -7.6381049999999995
  },
  "spadesdown_21_": {
    "width": 3.6341300000000003,
    "height": 0.35982,
    "x": 99.840185,
    "y": -45.663419999999995
  },
  "spadesdown_20_": {
    "width": 3.6341300000000003,
    "height": 0.35982,
    "x": 96.20604499999999,
    "y": -45.663419999999995
  },
  "spadesdown_19_": {
    "width": 3.6341300000000003,
    "height": 0.35982,
    "x": 92.57192500000001,
    "y": -45.663419999999995
  },
  "spadesdown_18_": {
    "width": 3.6341300000000003,
    "height": 0.35982,
    "x": 88.937785,
    "y": -45.663419999999995
  },
  "spadesdown_17_": {
    "width": 3.6341300000000003,
    "height": 0.35982,
    "x": 85.303665,
    "y": -45.663419999999995
  },
  "spadesdown_16_": {
    "width": 3.63411,
    "height": 0.35982,
    "x": 120.181665,
    "y": -45.663419999999995
  },
  "spadesdown_15_": {
    "width": 3.6341300000000003,
    "height": 0.35985,
    "x": 123.81577499999999,
    "y": -45.66343499999999
  },
  "spadesdown_13_": {
    "width": 3.6341300000000003,
    "height": 0.35982,
    "x": 127.449895,
    "y": -45.663419999999995
  },
  "spadesdown_12_": {
    "width": 3.6341300000000003,
    "height": 0.35982,
    "x": 131.08403500000003,
    "y": -45.663419999999995
  },
  "spadesdown_11_": {
    "width": 3.6341300000000003,
    "height": 0.35982,
    "x": 134.71815500000002,
    "y": -45.663419999999995
  },
  "spadesup_1_": {
    "width": 3.63412,
    "height": 0.35792,
    "x": 105.94683,
    "y": -39.29531
  },
  "spadesup_2_": {
    "width": 3.6341300000000003,
    "height": 0.35790999999999995,
    "x": 114.30048500000001,
    "y": -43.422345
  },
  "spadesup_4_": {
    "width": 3.63414,
    "height": 0.35792,
    "x": 89.23949,
    "y": -31.02531
  },
  "spadesup_3_": {
    "width": 3.63414,
    "height": 0.35792,
    "x": 97.59314,
    "y": -35.152339999999995
  },
  "spadesup_6_": {
    "width": 3.63414,
    "height": 0.35792,
    "x": 89.23949,
    "y": -22.787180000000003
  },
  "spadesup_5_": {
    "width": 3.63414,
    "height": 0.35792,
    "x": 97.59314,
    "y": -26.91421
  },
  "spadesup_8_": {
    "width": 3.63412,
    "height": 0.35792,
    "x": 105.94683,
    "y": -31.041249999999998
  },
  "platformcage4_64_": {
    "width": 3.63412,
    "height": 2.06352,
    "x": 105.94683,
    "y": -46.33866
  },
  "spadesup_39_": {
    "width": 3.63412,
    "height": 0.35790999999999995,
    "x": 105.94683,
    "y": -47.549375000000005
  },
  "spadesup_7_": {
    "width": 3.6341300000000003,
    "height": 0.35792,
    "x": 114.30048500000001,
    "y": -35.168279999999996
  },
  "spadesup_10_": {
    "width": 3.63411,
    "height": 0.35792,
    "x": 122.65416499999999,
    "y": -39.29531
  },
  "spadesup_9_": {
    "width": 3.6341300000000003,
    "height": 0.35790999999999995,
    "x": 131.00780500000002,
    "y": -43.422345
  },
  "spadesup_15_": {
    "width": 3.6341300000000003,
    "height": 0.35792,
    "x": 97.59315500000001,
    "y": -18.674210000000002
  },
  "spadesup_14_": {
    "width": 3.63414,
    "height": 0.35792,
    "x": 105.94684000000001,
    "y": -22.80125
  },
  "spadesup_13_": {
    "width": 3.6341300000000003,
    "height": 0.35792,
    "x": 114.30048500000001,
    "y": -26.928279999999997
  },
  "spadesup_12_": {
    "width": 3.63412,
    "height": 0.35792,
    "x": 122.65415999999999,
    "y": -31.055310000000002
  },
  "spadesup_11_": {
    "width": 3.6341300000000003,
    "height": 0.35792,
    "x": 131.00780500000002,
    "y": -35.182339999999996
  },
  "spadesup_19_": {
    "width": 3.63414,
    "height": 0.35792,
    "x": 105.94684000000001,
    "y": -14.53127
  },
  "spadesup_18_": {
    "width": 3.6341300000000003,
    "height": 0.35792,
    "x": 114.30048500000001,
    "y": -18.6583
  },
  "spadesup_16_": {
    "width": 3.6341300000000003,
    "height": 0.35792999999999997,
    "x": 131.00780500000002,
    "y": -26.912365000000005
  },
  "spadesup_21_": {
    "width": 3.6341300000000003,
    "height": 0.35792,
    "x": 114.30048500000001,
    "y": -10.406089999999999
  },
  "spadesup_20_": {
    "width": 3.63411,
    "height": 0.35792,
    "x": 122.65416499999999,
    "y": -14.53312
  },
  "spadesup_22_": {
    "width": 3.6341,
    "height": 0.35792,
    "x": 131.00790999999998,
    "y": -10.406089999999999
  },
  "spadesup_23_": {
    "width": 3.63412,
    "height": 0.35792,
    "x": 85.30368,
    "y": -9.37237
  },
  "spadesup_24_": {
    "width": 3.63412,
    "height": 0.35792,
    "x": 88.93780000000001,
    "y": -9.37237
  },
  "spadesup_26_": {
    "width": 3.63412,
    "height": 0.35792,
    "x": 92.57193,
    "y": -9.37237
  },
  "spadesup_25_": {
    "width": 3.63412,
    "height": 0.35792,
    "x": 96.20606,
    "y": -9.37237
  },
  "spadesup_27_": {
    "width": 3.63412,
    "height": 0.35792,
    "x": 99.84018,
    "y": -9.37237
  },
  "spadesup_32_": {
    "width": 3.63412,
    "height": 0.35792,
    "x": 103.47431,
    "y": -3.26405
  },
  "spadesup_31_": {
    "width": 3.63412,
    "height": 0.35792,
    "x": 107.10843,
    "y": -3.26405
  },
  "spadesup_30_": {
    "width": 3.63412,
    "height": 0.35792,
    "x": 110.74256,
    "y": -3.26405
  },
  "spadesup_29_": {
    "width": 3.63416,
    "height": 0.35792,
    "x": 114.3767,
    "y": -3.26405
  },
  "spadesup_28_": {
    "width": 3.63409,
    "height": 0.35792,
    "x": 118.010815,
    "y": -3.26405
  },
  "spadesup_37_": {
    "width": 3.63412,
    "height": 0.35792,
    "x": 121.64493,
    "y": -3.26405
  },
  "spadesup_36_": {
    "width": 3.63412,
    "height": 0.35792,
    "x": 125.27905,
    "y": -3.26405
  },
  "spadesup_35_": {
    "width": 3.63412,
    "height": 0.35792,
    "x": 128.91317,
    "y": -3.26405
  },
  "spadesup_34_": {
    "width": 3.63412,
    "height": 0.35792,
    "x": 132.54729999999998,
    "y": -3.26405
  },
  "groundcage3_88_": {
    "width": 8.35367,
    "height": 3.05416,
    "x": 80.773095,
    "y": -10.72049
  },
  "platformcage4_10_": {
    "width": 3.63414,
    "height": 2.06352,
    "x": 131.00781,
    "y": -17.44944
  },
  "spadesup_33_": {
    "width": 3.6341300000000003,
    "height": 0.35792,
    "x": 131.00780500000002,
    "y": -18.6583
  },
  "spadesup_17_": {
    "width": 3.63414,
    "height": 0.35792,
    "x": 122.65421,
    "y": -22.787180000000003
  },
  "groundcage1_83_": {
    "width": 8.35365,
    "height": 3.05416,
    "x": 80.773095,
    "y": -22.937130000000003
  },
  "platformcage3_36_": {
    "width": 3.63414,
    "height": 2.06352,
    "x": 116.57172,
    "y": -51.992779999999996
  },
  "platformcage3_35_": {
    "width": 3.6341300000000003,
    "height": 2.06352,
    "x": 120.20587499999999,
    "y": -51.992779999999996
  },
  "platformcage3_37_": {
    "width": 3.6341300000000003,
    "height": 2.06352,
    "x": 120.20587499999999,
    "y": -49.929249999999996
  },
  "pillevolutiond_5_": {
    "width": 0.50684,
    "height": 0.61856,
    "x": 114.04707,
    "y": -40.04428
  },
  "pillevolutionb_6_": {
    "width": 0.50686,
    "height": 0.61857,
    "x": 97.48043,
    "y": -23.598775
  },
  "pillevolutiond_6_": {
    "width": 0.50684,
    "height": 0.6185499999999999,
    "x": 105.94684000000001,
    "y": -19.573695
  },
  "pillevolutiona_1_": {
    "width": 0.50686,
    "height": 0.61854,
    "x": 80.77308,
    "y": -19.44656
  },
  "groundcage1_275_": {
    "width": 8.35366,
    "height": 3.05416,
    "x": 21.35151,
    "y": -22.938750000000002
  },
  "groundcage3_112_": {
    "width": 8.35367,
    "height": 3.0541699999999996,
    "x": 12.997854999999998,
    "y": -21.411685
  },
  "groundcage1_274_": {
    "width": 8.35368,
    "height": 3.05416,
    "x": 30.178150000000002,
    "y": -25.992910000000002
  },
  "groundcage1_273_": {
    "width": 8.35368,
    "height": 3.0541500000000004,
    "x": 30.178150000000002,
    "y": -22.938755
  },
  "groundcage1_268_": {
    "width": 8.35366,
    "height": 3.05416,
    "x": 21.824469999999998,
    "y": -25.992910000000002
  },
  "spadesdown_35_": {
    "width": 3.6341300000000003,
    "height": 0.35984,
    "x": 25.779745,
    "y": -24.285919999999997
  },
  "groundcage1_267_": {
    "width": 8.35367,
    "height": 3.05416,
    "x": 38.531814999999995,
    "y": -22.93878
  },
  "groundcage1_261_": {
    "width": 8.35367,
    "height": 3.0541500000000004,
    "x": 47.358444999999996,
    "y": -22.938795
  },
  "groundcage1_265_": {
    "width": 8.35367,
    "height": 3.05416,
    "x": 55.712115,
    "y": -22.93879
  },
  "groundcage1_113_": {
    "width": 8.35368,
    "height": 3.05416,
    "x": 72.41944,
    "y": -22.937130000000003
  },
  "groundcage1_1_": {
    "width": 8.35367,
    "height": 3.05416,
    "x": 64.065795,
    "y": -22.937130000000003
  },
  "groundcage3_110_": {
    "width": 8.35367,
    "height": 3.05416,
    "x": 38.531805,
    "y": -25.99293
  },
  "groundcage3_111_": {
    "width": 8.35367,
    "height": 3.05416,
    "x": 47.35843499999999,
    "y": -25.99295
  },
  "groundcage1_287_": {
    "width": 8.35367,
    "height": 3.05416,
    "x": 38.531805,
    "y": -32.10125
  },
  "groundcage4_6_": {
    "width": 8.35367,
    "height": 3.05416,
    "x": 38.531805,
    "y": -36.682449999999996
  },
  "groundcage1_288_": {
    "width": 8.35367,
    "height": 3.05416,
    "x": 47.35843499999999,
    "y": -36.682449999999996
  },
  "groundcage1_296_": {
    "width": 8.35367,
    "height": 3.05416,
    "x": 21.351505000000003,
    "y": -36.682449999999996
  },
  "groundcage1_294_": {
    "width": 8.35367,
    "height": 3.05416,
    "x": 30.178135,
    "y": -36.682449999999996
  },
  "groundcage1_292_": {
    "width": 8.35368,
    "height": 3.0541500000000004,
    "x": 12.52487,
    "y": -42.787475
  },
  "spadesdown_33_": {
    "width": 3.6341300000000003,
    "height": 0.35982,
    "x": 8.599425,
    "y": -41.08049
  },
  "groundcage1_330_": {
    "width": 8.35367,
    "height": 3.0541500000000004,
    "x": 26.184865,
    "y": -42.787475
  },
  "spadesdown_32_": {
    "width": 3.6341300000000003,
    "height": 0.35982,
    "x": 25.868045,
    "y": -41.08049
  },
  "groundcage3_109_": {
    "width": 8.35366,
    "height": 3.05416,
    "x": 4.17119,
    "y": -35.155409999999996
  },
  "groundcage4_7_": {
    "width": 8.35367,
    "height": 3.0541500000000004,
    "x": 12.997834999999998,
    "y": -36.679205
  },
  "groundcage1_337_": {
    "width": 8.35368,
    "height": 3.0541500000000004,
    "x": 43.35201,
    "y": -42.784665000000004
  },
  "spadesdown_31_": {
    "width": 3.6341300000000003,
    "height": 0.35982,
    "x": 43.035185,
    "y": -41.07767
  },
  "groundcage1_129_": {
    "width": 8.35367,
    "height": 3.05416,
    "x": 55.712095,
    "y": -36.6825
  },
  "groundcage3_108_": {
    "width": 8.35367,
    "height": 3.0541500000000004,
    "x": 64.538725,
    "y": -38.209585000000004
  },
  "spadesdown_34_": {
    "width": 3.63414,
    "height": 0.35983,
    "x": 61.018789999999996,
    "y": -38.029665
  },
  "pillevolutionb_1_": {
    "width": 0.50686,
    "height": 0.61857,
    "x": 106.20026,
    "y": -44.316245
  },
  "pillevolutionb_7_": {
    "width": 0.50686,
    "height": 0.61857,
    "x": 105.66938999999999,
    "y": -52.715244999999996
  },
  "shadows_7_": {
    "width": 24.875999999999998,
    "height": 19.89326,
    "x": 99.93673,
    "y": -66.96151
  },
  "groundcage3_19_": {
    "width": 8.35366,
    "height": 3.05416,
    "x": 30.65122,
    "y": -93.18281
  },
  "groundcage3_18_": {
    "width": 8.35366,
    "height": 3.05416,
    "x": 30.65122,
    "y": -90.12865
  },
  "groundcage3_17_": {
    "width": 8.35366,
    "height": 3.05416,
    "x": 30.65122,
    "y": -87.07449
  },
  "groundcage3_16_": {
    "width": 8.35366,
    "height": 3.05416,
    "x": 30.65122,
    "y": -84.02033
  },
  "groundcage3_23_": {
    "width": 8.35366,
    "height": 3.05416,
    "x": 47.35856,
    "y": -105.39944999999999
  },
  "groundcage3_22_": {
    "width": 8.35366,
    "height": 3.05416,
    "x": 47.35856,
    "y": -102.34528999999999
  },
  "groundcage3_21_": {
    "width": 8.35366,
    "height": 3.05416,
    "x": 47.35856,
    "y": -99.29113000000001
  },
  "groundcage3_20_": {
    "width": 8.35366,
    "height": 3.05416,
    "x": 47.35856,
    "y": -96.23697
  },
  "groundcage3_27_": {
    "width": 8.35366,
    "height": 3.05416,
    "x": 47.35856,
    "y": -93.18281
  },
  "groundcage3_26_": {
    "width": 8.35366,
    "height": 3.05416,
    "x": 47.35856,
    "y": -90.12865
  },
  "groundcage3_25_": {
    "width": 8.35366,
    "height": 3.05416,
    "x": 47.35856,
    "y": -87.07449
  },
  "groundcage3_24_": {
    "width": 8.35366,
    "height": 3.05416,
    "x": 47.35856,
    "y": -84.02033
  },
  "groundcage3_31_": {
    "width": 8.35366,
    "height": 3.05416,
    "x": 72.41954,
    "y": -114.56193
  },
  "groundcage3_30_": {
    "width": 8.35366,
    "height": 3.05416,
    "x": 72.41954,
    "y": -111.50777
  },
  "groundcage3_29_": {
    "width": 8.35366,
    "height": 3.05416,
    "x": 72.41954,
    "y": -108.45361
  },
  "groundcage3_28_": {
    "width": 8.35366,
    "height": 3.05416,
    "x": 72.41954,
    "y": -105.39944999999999
  },
  "groundcage3_35_": {
    "width": 8.35366,
    "height": 3.05416,
    "x": 72.41954,
    "y": -102.34528999999999
  },
  "groundcage3_34_": {
    "width": 8.35366,
    "height": 3.05416,
    "x": 72.41954,
    "y": -99.29113000000001
  },
  "groundcage3_33_": {
    "width": 8.35366,
    "height": 3.05416,
    "x": 72.41954,
    "y": -96.23697
  },
  "groundcage3_32_": {
    "width": 8.35366,
    "height": 3.05416,
    "x": 72.41954,
    "y": -93.18281
  },
  "groundcage3_38_": {
    "width": 8.35366,
    "height": 3.05416,
    "x": 72.41954,
    "y": -90.12865
  },
  "groundcage3_37_": {
    "width": 8.35366,
    "height": 3.05416,
    "x": 72.41954,
    "y": -87.07449
  },
  "groundcage3_36_": {
    "width": 8.35366,
    "height": 3.05416,
    "x": 72.41954,
    "y": -84.02033
  },
  "groundcage1_7_": {
    "width": 8.35364,
    "height": 3.05416,
    "x": 39.004889999999996,
    "y": -77.91196000000001
  },
  "groundcage1_8_": {
    "width": 8.35364,
    "height": 3.05416,
    "x": 47.35856,
    "y": -77.91196000000001
  },
  "groundcage1_10_": {
    "width": 8.35364,
    "height": 3.05416,
    "x": 22.29756,
    "y": -77.91196000000001
  },
  "groundcage1_9_": {
    "width": 8.35364,
    "height": 3.05416,
    "x": 30.651229999999998,
    "y": -77.91196000000001
  },
  "characterstart_4_": {
    "width": 0.85193,
    "height": 4.03363,
    "x": 37.610195,
    "y": -114.03376499999999
  },
  "groundcage3_48_": {
    "width": 8.35366,
    "height": 3.05416,
    "x": 22.29756,
    "y": -74.88772
  },
  "groundcage3_47_": {
    "width": 8.35366,
    "height": 3.05416,
    "x": 22.29756,
    "y": -71.83356
  },
  "groundcage3_46_": {
    "width": 8.35366,
    "height": 3.05416,
    "x": 22.29756,
    "y": -68.7794
  },
  "groundcage3_45_": {
    "width": 8.35366,
    "height": 3.05416,
    "x": 22.29756,
    "y": -65.72524
  },
  "groundcage3_44_": {
    "width": 8.35366,
    "height": 3.05416,
    "x": 22.29756,
    "y": -62.671079999999996
  },
  "groundcage3_43_": {
    "width": 8.35366,
    "height": 3.05416,
    "x": 22.29756,
    "y": -59.61692
  },
  "groundcage3_42_": {
    "width": 8.35366,
    "height": 3.05416,
    "x": 22.29756,
    "y": -56.56276
  },
  "groundcage3_41_": {
    "width": 8.35366,
    "height": 3.05416,
    "x": 22.29756,
    "y": -53.5086
  },
  "groundcage3_51_": {
    "width": 8.35366,
    "height": 3.05416,
    "x": 55.71215,
    "y": -63.6185
  },
  "groundcage3_50_": {
    "width": 8.35366,
    "height": 3.05416,
    "x": 55.71215,
    "y": -60.564339999999994
  },
  "groundcage3_49_": {
    "width": 8.35366,
    "height": 3.05416,
    "x": 55.71215,
    "y": -57.510180000000005
  },
  "groundcage3_39_": {
    "width": 8.35366,
    "height": 3.05416,
    "x": 55.71215,
    "y": -54.45602
  },
  "groundcage3_57_": {
    "width": 8.35366,
    "height": 3.05416,
    "x": 147.60247,
    "y": -77.91201
  },
  "groundcage3_56_": {
    "width": 8.35366,
    "height": 3.05416,
    "x": 147.60247,
    "y": -74.85785
  },
  "groundcage3_55_": {
    "width": 8.35366,
    "height": 3.05416,
    "x": 147.60247,
    "y": -71.80369
  },
  "groundcage3_54_": {
    "width": 8.35366,
    "height": 3.05416,
    "x": 147.60247,
    "y": -68.74953
  },
  "groundcage3_53_": {
    "width": 8.35366,
    "height": 3.05416,
    "x": 147.60247,
    "y": -65.69537
  },
  "groundcage3_52_": {
    "width": 8.35366,
    "height": 3.05416,
    "x": 147.60247,
    "y": -62.641209999999994
  },
  "groundcage3_60_": {
    "width": 8.35366,
    "height": 3.05416,
    "x": 147.60247,
    "y": -59.58705
  },
  "groundcage3_59_": {
    "width": 8.35366,
    "height": 3.05416,
    "x": 147.60247,
    "y": -56.53289
  },
  "groundcage3_58_": {
    "width": 8.35366,
    "height": 3.05416,
    "x": 147.60247,
    "y": -53.47873
  },
  "groundcage3_66_": {
    "width": 8.35366,
    "height": 3.05416,
    "x": 155.95611,
    "y": -47.37040999999999
  },
  "groundcage3_65_": {
    "width": 8.35366,
    "height": 3.05416,
    "x": 155.95611,
    "y": -44.316250000000004
  },
  "groundcage3_64_": {
    "width": 8.35366,
    "height": 3.05416,
    "x": 155.95611,
    "y": -41.26208
  },
  "groundcage3_63_": {
    "width": 8.35366,
    "height": 3.05416,
    "x": 155.95611,
    "y": -38.207919999999994
  },
  "groundcage3_62_": {
    "width": 8.35366,
    "height": 3.05416,
    "x": 155.95611,
    "y": -35.15376
  },
  "groundcage3_61_": {
    "width": 8.35366,
    "height": 3.05416,
    "x": 155.95611,
    "y": -32.0996
  },
  "groundcage3_72_": {
    "width": 8.35366,
    "height": 3.05416,
    "x": 155.95611,
    "y": -29.045450000000002
  },
  "groundcage3_71_": {
    "width": 8.35366,
    "height": 3.05416,
    "x": 155.95611,
    "y": -25.99129
  },
  "groundcage3_70_": {
    "width": 8.35366,
    "height": 3.05416,
    "x": 155.95611,
    "y": -22.937130000000003
  },
  "groundcage3_69_": {
    "width": 8.35366,
    "height": 3.05416,
    "x": 155.95611,
    "y": -19.88297
  },
  "groundcage3_68_": {
    "width": 8.35366,
    "height": 3.05416,
    "x": 155.95611,
    "y": -16.82881
  },
  "groundcage3_67_": {
    "width": 8.35366,
    "height": 3.05416,
    "x": 155.95611,
    "y": -13.774650000000001
  },
  "groundcage3_75_": {
    "width": 8.35366,
    "height": 3.05416,
    "x": 155.95611,
    "y": -10.72049
  },
  "groundcage3_74_": {
    "width": 8.35366,
    "height": 3.05416,
    "x": 155.95611,
    "y": -7.666329999999999
  },
  "groundcage3_73_": {
    "width": 8.35366,
    "height": 3.05416,
    "x": 155.95611,
    "y": -4.61217
  },
  "groundcage3_81_": {
    "width": 8.35366,
    "height": 3.05416,
    "x": 139.24872,
    "y": -44.325649999999996
  },
  "groundcage3_80_": {
    "width": 8.35366,
    "height": 3.05416,
    "x": 139.24872,
    "y": -41.27148999999999
  },
  "groundcage3_79_": {
    "width": 8.35366,
    "height": 3.05416,
    "x": 139.24872,
    "y": -38.21733
  },
  "groundcage3_78_": {
    "width": 8.35366,
    "height": 3.05416,
    "x": 139.24872,
    "y": -35.163169999999994
  },
  "groundcage3_77_": {
    "width": 8.35366,
    "height": 3.05416,
    "x": 139.24872,
    "y": -32.109010000000005
  },
  "groundcage3_76_": {
    "width": 8.35366,
    "height": 3.05416,
    "x": 139.24872,
    "y": -29.054850000000002
  },
  "groundcage3_84_": {
    "width": 8.35366,
    "height": 3.05416,
    "x": 139.24872,
    "y": -26.00069
  },
  "groundcage3_83_": {
    "width": 8.35366,
    "height": 3.05416,
    "x": 139.24872,
    "y": -22.946530000000003
  },
  "groundcage3_82_": {
    "width": 8.35366,
    "height": 3.05416,
    "x": 139.24872,
    "y": -19.892370000000003
  },
  "groundcage3_86_": {
    "width": 8.35366,
    "height": 3.05416,
    "x": 139.24872,
    "y": -16.83821
  },
  "groundcage3_85_": {
    "width": 8.35366,
    "height": 3.05416,
    "x": 139.24872,
    "y": -13.784049999999999
  },
  "groundcage3_92_": {
    "width": 8.35366,
    "height": 3.05416,
    "x": 80.77309,
    "y": -32.10123
  },
  "groundcage3_91_": {
    "width": 8.35366,
    "height": 3.05416,
    "x": 80.77309,
    "y": -29.047069999999998
  },
  "groundcage3_90_": {
    "width": 8.35366,
    "height": 3.05416,
    "x": 80.77309,
    "y": -25.992910000000002
  },
  "groundcage3_95_": {
    "width": 8.35366,
    "height": 3.05416,
    "x": 80.77309,
    "y": -41.263709999999996
  },
  "groundcage3_96_": {
    "width": 8.35366,
    "height": 3.05416,
    "x": 80.77309,
    "y": -44.31786999999999
  },
  "groundcage3_94_": {
    "width": 8.35366,
    "height": 3.05416,
    "x": 80.77309,
    "y": -38.20954999999999
  },
  "groundcage3_93_": {
    "width": 8.35366,
    "height": 3.05416,
    "x": 80.77309,
    "y": -35.15539
  },
  "groundcage3_97_": {
    "width": 8.35366,
    "height": 3.05416,
    "x": 47.35843,
    "y": -29.047069999999998
  },
  "groundcage3_98_": {
    "width": 8.35366,
    "height": 3.05416,
    "x": 38.53181,
    "y": -29.047069999999998
  },
  "groundcage3_100_": {
    "width": 8.35366,
    "height": 3.05416,
    "x": 4.17119,
    "y": -38.20628
  },
  "groundcage3_101_": {
    "width": 8.35366,
    "height": 3.05416,
    "x": 4.17119,
    "y": -41.2604
  },
  "groundcage3_102_": {
    "width": 8.35366,
    "height": 3.05416,
    "x": 12.99783,
    "y": -39.73336
  },
  "groundcage3_103_": {
    "width": 8.35366,
    "height": 3.05416,
    "x": 21.3515,
    "y": -39.73336
  },
  "groundcage3_104_": {
    "width": 8.35366,
    "height": 3.05416,
    "x": 30.17813,
    "y": -39.73052
  },
  "groundcage3_105_": {
    "width": 8.35366,
    "height": 3.05416,
    "x": 38.53181,
    "y": -39.73052
  },
  "groundcage3_106_": {
    "width": 8.35366,
    "height": 3.05416,
    "x": 47.35843,
    "y": -39.73052
  },
  "groundcage4": {
    "width": 8.35366,
    "height": 3.05416,
    "x": 56.18506000000001,
    "y": -39.73666
  },
  "groundcage3_107_": {
    "width": 8.35366,
    "height": 3.05416,
    "x": 64.53873,
    "y": -35.15542
  },
  "groundcage2_1_": {
    "width": 8.35365,
    "height": 3.05416,
    "x": 30.651235,
    "y": -80.96616999999999
  },
  "groundcage2_3_": {
    "width": 8.35365,
    "height": 3.05416,
    "x": 22.297565000000002,
    "y": -80.96616999999999
  },
  "groundcage2_2_": {
    "width": 8.35365,
    "height": 3.05416,
    "x": 13.943905,
    "y": -80.96616999999999
  },
  "groundcage2_4_": {
    "width": 8.35365,
    "height": 3.05416,
    "x": 5.590245,
    "y": -80.96616999999999
  },
  "groundcage2_5_": {
    "width": 8.35365,
    "height": 3.05416,
    "x": 22.297565000000002,
    "y": -50.45444
  },
  "groundcage2_6_": {
    "width": 8.35365,
    "height": 3.05416,
    "x": 30.651225,
    "y": -50.45444
  },
  "groundcage2_7_": {
    "width": 8.35365,
    "height": 3.05416,
    "x": 39.004875,
    "y": -50.45444
  },
  "groundcage2_8_": {
    "width": 8.35365,
    "height": 3.05416,
    "x": 47.358525,
    "y": -50.45444
  },
  "groundcage2_9_": {
    "width": 8.35364,
    "height": 3.05416,
    "x": 55.71215,
    "y": -48.347680000000004
  },
  "groundcage2_10_": {
    "width": 8.35364,
    "height": 3.05416,
    "x": 72.41944000000001,
    "y": -47.37040999999999
  },
  "groundcage2_11_": {
    "width": 8.35364,
    "height": 3.05416,
    "x": 64.06578,
    "y": -47.37040999999999
  },
  "groundcage2_13_": {
    "width": 8.35364,
    "height": 3.05416,
    "x": 72.41944000000001,
    "y": -18.355890000000002
  },
  "groundcage2_14_": {
    "width": 8.35364,
    "height": 3.0541500000000004,
    "x": 64.06579,
    "y": -18.355895
  },
  "groundcage2_16_": {
    "width": 8.35364,
    "height": 3.05416,
    "x": 55.71214,
    "y": -18.355900000000002
  },
  "groundcage2_15_": {
    "width": 8.35364,
    "height": 3.0541500000000004,
    "x": 47.35849,
    "y": -18.355895
  },
  "groundcage2_20_": {
    "width": 8.35364,
    "height": 3.05416,
    "x": 39.00485,
    "y": -18.355900000000002
  },
  "groundcage2_19_": {
    "width": 8.35364,
    "height": 3.0541500000000004,
    "x": 30.6512,
    "y": -18.355895
  },
  "groundcage2_18_": {
    "width": 8.35364,
    "height": 3.05416,
    "x": 22.29755,
    "y": -18.355900000000002
  },
  "groundcage2_17_": {
    "width": 8.35364,
    "height": 3.0541500000000004,
    "x": 13.9439,
    "y": -18.355905
  },
  "groundcage2_23_": {
    "width": 8.35364,
    "height": 3.0541500000000004,
    "x": 64.06575000000001,
    "y": -32.101245
  },
  "groundcage2_22_": {
    "width": 8.35364,
    "height": 3.05416,
    "x": 55.7121,
    "y": -32.10125
  },
  "groundcage2_21_": {
    "width": 8.35364,
    "height": 3.05416,
    "x": 47.35845,
    "y": -32.10125
  },
  "groundcage2_26_": {
    "width": 8.35364,
    "height": 3.0541500000000004,
    "x": 30.17812,
    "y": -32.101245
  },
  "groundcage2_25_": {
    "width": 8.35364,
    "height": 3.05416,
    "x": 21.82448,
    "y": -32.10125
  },
  "groundcage2_24_": {
    "width": 8.35364,
    "height": 3.05416,
    "x": 13.47083,
    "y": -32.10125
  },
  "groundcage2_27_": {
    "width": 8.35364,
    "height": 3.05416,
    "x": 5.11719,
    "y": -32.10125
  },
  "groundcage2_30_": {
    "width": 8.35365,
    "height": 3.0541500000000004,
    "x": 97.48036499999999,
    "y": -7.666325
  },
  "groundcage2_29_": {
    "width": 8.35364,
    "height": 3.05416,
    "x": 89.12672,
    "y": -7.666329999999999
  },
  "groundcage2_28_": {
    "width": 8.35363,
    "height": 3.0541500000000004,
    "x": 80.773075,
    "y": -7.666325
  },
  "groundcage2_34_": {
    "width": 8.35365,
    "height": 3.0541500000000004,
    "x": 114.18769499999999,
    "y": -1.558005
  },
  "groundcage2_33_": {
    "width": 8.35364,
    "height": 3.05416,
    "x": 105.83405,
    "y": -1.55801
  },
  "groundcage2_32_": {
    "width": 8.35363,
    "height": 3.0541500000000004,
    "x": 97.480395,
    "y": -1.558005
  },
  "groundcage2_37_": {
    "width": 8.35365,
    "height": 3.0541500000000004,
    "x": 139.248625,
    "y": -1.558005
  },
  "groundcage2_36_": {
    "width": 8.35364,
    "height": 3.05416,
    "x": 130.89498,
    "y": -1.55801
  },
  "groundcage2_35_": {
    "width": 8.35363,
    "height": 3.0541500000000004,
    "x": 122.541325,
    "y": -1.558005
  },
  "groundcage2_39_": {
    "width": 8.35364,
    "height": 3.05416,
    "x": 155.95592,
    "y": -1.55802
  },
  "groundcage2_38_": {
    "width": 8.35363,
    "height": 3.0541500000000004,
    "x": 147.60226500000002,
    "y": -1.5580150000000001
  }
}